sentinel/__init__.py
sentinel/audit.py
sentinel/cli.py
sentinel/core.py
sentinel/engine.py
sentinel/factory.py
sentinel/integration.py
sentinel/presidio_adapter.py
sentinel/streaming.py
sentinel/topic_guardrail.py
sentinel/utils.py
sentinel/defaults/injection_guardrail.py
sentinel/defaults/pii_guardrail.py
sentinel/defaults/profanity_guardrail.py
sentinel/defaults/secret_guardrail.py
sentinel/integrations/huggingface.py
sentinel/integrations/langchain.py
sentinel/integrations/llamaindex.py
sentinel/integrations/openai.py
sentinel/plugins/__init__.py
sentinel/plugins/base.py
sentinel/plugins/langkit_plugin.py
sentinel/profiles/__init__.py
sentinel/profiles/default.yaml
sentinel/profiles/finance.yaml
sentinel/profiles/healthcare.yaml
sentinel/profiles/hybrid.yaml
sentinel/profiles/plugins_demo.yaml
sentinel/profiles/presidio_pro.yaml
sentinel/profiles/custom/test_custom_v5.yaml
semantic_sentinel-1.0.0.dist-info/METADATA
semantic_sentinel-1.0.0.dist-info/WHEEL
semantic_sentinel-1.0.0.dist-info/entry_points.txt
semantic_sentinel-1.0.0.dist-info/licenses/LICENSE
semantic_sentinel-1.0.0.dist-info/RECORD
