Metadata-Version: 2.4
Name: semantic-sentinel
Version: 1.0.0
Summary: Enterprise-grade Security Framework for LLMs
Project-URL: Homepage, https://github.com/rarenicks/semantic-sentinel
Project-URL: Documentation, https://github.com/rarenicks/semantic-sentinel/tree/main/docs
Project-URL: Repository, https://github.com/rarenicks/semantic-sentinel
Project-URL: Issues, https://github.com/rarenicks/semantic-sentinel/issues
Project-URL: Changelog, https://github.com/rarenicks/semantic-sentinel/blob/main/CHANGELOG.md
Author-email: Avdhesh Singh Chouhan <ai.avdhesh@gmail.com>
License-Expression: MIT
License-File: LICENSE
Keywords: ai,firewall,guardrails,injection,llm,pii,security
Classifier: Development Status :: 3 - Alpha
Classifier: License :: OSI Approved :: MIT License
Classifier: Operating System :: OS Independent
Classifier: Programming Language :: Python :: 3.10
Classifier: Programming Language :: Python :: 3.11
Classifier: Topic :: Scientific/Engineering :: Artificial Intelligence
Classifier: Topic :: Security
Requires-Python: >=3.10
Requires-Dist: presidio-analyzer
Requires-Dist: presidio-anonymizer
Requires-Dist: pydantic>=2.9.2
Requires-Dist: pyyaml>=6.0
Requires-Dist: scikit-learn
Requires-Dist: sentence-transformers
Requires-Dist: spacy
Provides-Extra: all
Requires-Dist: detoxify; extra == 'all'
Requires-Dist: fastapi>=0.115.0; extra == 'all'
Requires-Dist: guardrails-ai; extra == 'all'
Requires-Dist: httpx>=0.27.2; extra == 'all'
Requires-Dist: langchain-core>=0.3.0; extra == 'all'
Requires-Dist: langkit; extra == 'all'
Requires-Dist: llama-index-core>=0.10.0; extra == 'all'
Requires-Dist: openai>=1.0.0; extra == 'all'
Requires-Dist: python-dotenv>=1.0.1; extra == 'all'
Requires-Dist: uvicorn>=0.31.1; extra == 'all'
Requires-Dist: whylogs[langkit]; extra == 'all'
Provides-Extra: api
Requires-Dist: fastapi>=0.115.0; extra == 'api'
Requires-Dist: httpx>=0.27.2; extra == 'api'
Requires-Dist: python-dotenv>=1.0.1; extra == 'api'
Requires-Dist: uvicorn>=0.31.1; extra == 'api'
Provides-Extra: dev
Requires-Dist: mypy; extra == 'dev'
Requires-Dist: pytest; extra == 'dev'
Requires-Dist: pytest-asyncio; extra == 'dev'
Requires-Dist: ruff; extra == 'dev'
Provides-Extra: integrations
Requires-Dist: langchain-core>=0.3.0; extra == 'integrations'
Requires-Dist: llama-index-core>=0.10.0; extra == 'integrations'
Requires-Dist: openai>=1.0.0; extra == 'integrations'
Provides-Extra: langchain
Requires-Dist: langchain-core>=0.3.0; extra == 'langchain'
Provides-Extra: llamaindex
Requires-Dist: llama-index-core>=0.10.0; extra == 'llamaindex'
Provides-Extra: openai
Requires-Dist: openai>=1.0.0; extra == 'openai'
Provides-Extra: plugins
Requires-Dist: detoxify; extra == 'plugins'
Requires-Dist: guardrails-ai; extra == 'plugins'
Requires-Dist: langkit; extra == 'plugins'
Requires-Dist: whylogs[langkit]; extra == 'plugins'
